es_wait/__init__.py
es_wait/_base.py
es_wait/debug.py
es_wait/defaults.py
es_wait/exceptions.py
es_wait/exists.py
es_wait/health.py
es_wait/ilm.py
es_wait/py.typed
es_wait/relocate.py
es_wait/restore.py
es_wait/snapshot.py
es_wait/task.py
es_wait/utils.py
es_wait-0.15.1.dist-info/METADATA
es_wait-0.15.1.dist-info/WHEEL
es_wait-0.15.1.dist-info/licenses/LICENSE
es_wait-0.15.1.dist-info/RECORD
