Metadata-Version: 2.4
Name: es-wait
Version: 0.15.1
Summary: Helping you wait for certain Elasticsearch tasks and API calls to finish
Project-URL: Documentation, https://github.com/untergeek/es-wait#readme
Project-URL: Issues, https://github.com/untergeek/es-wait/issues
Project-URL: Source, https://github.com/untergeek/es-wait
Author-email: Aaron Mildenstein <untergeek@elastic.co>
License: Apache-2.0
License-File: LICENSE
Keywords: elasticsearch,tools,wait
Classifier: Intended Audience :: Developers
Classifier: Intended Audience :: System Administrators
Classifier: License :: OSI Approved :: Apache Software License
Classifier: Operating System :: OS Independent
Classifier: Programming Language :: Python
Classifier: Programming Language :: Python :: 3.8
Classifier: Programming Language :: Python :: 3.9
Classifier: Programming Language :: Python :: 3.10
Classifier: Programming Language :: Python :: 3.11
Classifier: Programming Language :: Python :: 3.12
Classifier: Programming Language :: Python :: 3.13
Requires-Python: >=3.8
Requires-Dist: dotmap==1.3.30
Requires-Dist: elasticsearch8>=8.18.0
Requires-Dist: tiered-debug==1.3.0
Provides-Extra: doc
Requires-Dist: furo>=2024.8.6; extra == 'doc'
Provides-Extra: test
Requires-Dist: es-client>=8.18.2; extra == 'test'
Requires-Dist: mock; extra == 'test'
Requires-Dist: pytest-cov; extra == 'test'
Requires-Dist: pytest>=7.2.1; extra == 'test'
Requires-Dist: python-dotenv==1.0.1; extra == 'test'
Requires-Dist: requests; extra == 'test'
